modelcraft/__init__.py
modelcraft/__main__.py
modelcraft/arguments.py
modelcraft/cell.py
modelcraft/combine.py
modelcraft/contents.py
modelcraft/environ.py
modelcraft/geometry.py
modelcraft/job.py
modelcraft/maps.py
modelcraft/modelcraftem.py
modelcraft/modelcraftxray.py
modelcraft/monlib.py
modelcraft/pipeline.py
modelcraft/reflections.py
modelcraft/solvent.py
modelcraft/structure.py
modelcraft/utils.py
modelcraft/coot/prune.py
modelcraft/coot/sidechains.py
modelcraft/jobs/__init__.py
modelcraft/jobs/acedrg.py
modelcraft/jobs/acorn.py
modelcraft/jobs/buccaneer.py
modelcraft/jobs/comit.py
modelcraft/jobs/coot.py
modelcraft/jobs/ctruncate.py
modelcraft/jobs/emda.py
modelcraft/jobs/findwaters.py
modelcraft/jobs/freerflag.py
modelcraft/jobs/libg.py
modelcraft/jobs/molrep.py
modelcraft/jobs/nautilus.py
modelcraft/jobs/parrot.py
modelcraft/jobs/phasematch.py
modelcraft/jobs/refmac.py
modelcraft/jobs/servalcat.py
modelcraft/jobs/sheetbend.py
modelcraft/scripts/__init__.py
modelcraft/scripts/contents.py
modelcraft/scripts/copies.py
modelcraft/scripts/modelcraft.py
modelcraft/tests/__init__.py
modelcraft/tests/ccp4/__init__.py
modelcraft/tests/ccp4/test_acedrg.py
modelcraft/tests/ccp4/test_arguments.py
modelcraft/tests/ccp4/test_buccaneer.py
modelcraft/tests/ccp4/test_cell.py
modelcraft/tests/ccp4/test_comit.py
modelcraft/tests/ccp4/test_contents.py
modelcraft/tests/ccp4/test_coot.py
modelcraft/tests/ccp4/test_copies.py
modelcraft/tests/ccp4/test_ctruncate.py
modelcraft/tests/ccp4/test_findwaters.py
modelcraft/tests/ccp4/test_freerflag.py
modelcraft/tests/ccp4/test_geometry.py
modelcraft/tests/ccp4/test_libg.py
modelcraft/tests/ccp4/test_molrep.py
modelcraft/tests/ccp4/test_monlib.py
modelcraft/tests/ccp4/test_nautilus.py
modelcraft/tests/ccp4/test_parrot.py
modelcraft/tests/ccp4/test_phasematch.py
modelcraft/tests/ccp4/test_reflections.py
modelcraft/tests/ccp4/test_refmac.py
modelcraft/tests/ccp4/test_sheetbend.py
modelcraft/tests/ccp4/test_solvent.py
modelcraft-5.0.3.dist-info/licenses/LICENSE
modelcraft-5.0.3.dist-info/METADATA
modelcraft-5.0.3.dist-info/WHEEL
modelcraft-5.0.3.dist-info/entry_points.txt
modelcraft-5.0.3.dist-info/top_level.txt
modelcraft-5.0.3.dist-info/RECORD
