Metadata-Version: 2.4
Name: modelcraft
Version: 5.0.3
Summary: Automated model building pipeline for X-ray crystallography
Home-page: https://github.com/paulsbond/modelcraft
Author: Paul Bond
Author-email: paul.bond@york.ac.uk
License: LGPL-2.1
Classifier: License :: OSI Approved :: GNU Lesser General Public License v2 or later (LGPLv2+)
Classifier: Operating System :: OS Independent
Classifier: Programming Language :: Python
Classifier: Programming Language :: Python :: 3
Classifier: Programming Language :: Python :: 3.7
Classifier: Programming Language :: Python :: 3.8
Classifier: Programming Language :: Python :: 3.9
Requires-Python: ~=3.7
License-File: LICENSE
Requires-Dist: gemmi>=0.5.5
Requires-Dist: numpy
Requires-Dist: pandas
Requires-Dist: requests
Requires-Dist: scipy
Dynamic: author
Dynamic: author-email
Dynamic: classifier
Dynamic: description
Dynamic: description-content-type
Dynamic: home-page
Dynamic: license
Dynamic: license-file
Dynamic: requires-dist
Dynamic: requires-python
Dynamic: summary
